{
  "title": "Shangrila Spring Beauty 2025",
  "name": "Nepal Shangrila First Flush 2025",
  "description": "Lehký jarní vysokohorský polozelený čaj s sladkou, svěží chutí a vůní připomínající jarní byliny a kvítí s dlouhou větrovou dochutí.",
  "types": [ "Oolong" ],
  "vendor": "Meetea",
  "url": "https://store.meetea.cz/kveten-2025/shangrila-spring-beauty-2025/",
  "origin": "Zahrada Shangrila, Nepál",
  "cultivar": "Clonal",
  "season": "Spring 2025",
  "elevation": "N/A",
  "price": "N/A",
  "brewingInstructions": "90°C, 4g/100ml, 40s-20s-30s-30s-40s",
  "inStock": false,
  "tags": [ "meetea-2025-may" ]
}
